<?xml version="1.0" encoding="UTF-8"?>

<!-- generated on 2025-07-13 22:44:51 by Eclipse SUMO GUI Version 1.22.0
<sumoConfiguration xmlns:xsi="http://www.w3.org/2001/XMLSchema-instance" xsi:noNamespaceSchemaLocation="http://sumo.dlr.de/xsd/sumoConfiguration.xsd">

    <input>
        <net-file value="C:/Users/DELL LATITUDE E7250/Desktop/Masters Research/v7/CenturyCityNode1_V1.net.xml"/>
        <route-files value="C:/Users/DELL LATITUDE E7250/Desktop/Masters Research/v7/CenturyCityNode1_V1.rou.xml"/>
        <additional-files value="C:/Users/DELL LATITUDE E7250/Desktop/Masters Research/v7/CenturyCityNode1_V1.add.xml"/>
    </input>

    <time>
        <step-length value="1.0"/>
    </time>

    <processing>
        <lateral-resolution value="0"/>
        <ignore-junction-blocker value="2"/>
    </processing>

    <report>
        <no-warnings value="true"/>
    </report>

    <traci_server>
        <remote-port value="60597"/>
    </traci_server>

    <gui_only>
        <delay value="1"/>
    </gui_only>

</sumoConfiguration>
-->

<detector xmlns:xsi="http://www.w3.org/2001/XMLSchema-instance" xsi:noNamespaceSchemaLocation="http://sumo.dlr.de/xsd/det_e2_file.xsd">
   <interval begin="0.00" end="82.00" id="Node4_WB_1" sampledSeconds="12.55" nVehEntered="4" nVehLeft="3" nVehSeen="4" meanSpeed="2.32" meanTimeLoss="2.74" meanOccupancy="5.05" maxOccupancy="50.55" meanMaxJamLengthInVehicles="0.07" meanMaxJamLengthInMeters="0.24" maxJamLengthInVehicles="1" maxJamLengthInMeters="5.00" jamLengthInVehiclesSum="6" jamLengthInMetersSum="20.04" meanHaltingDuration="3.00" maxHaltingDuration="5.00" haltingDurationSum="6.00" meanIntervalHaltingDuration="3.00" maxIntervalHaltingDuration="5.00" intervalHaltingDurationSum="6.00" startedHalts="3.00" meanVehicleNumber="0.17" maxVehicleNumber="2" />
</detector>
